pystocktopus/GUI.py
pystocktopus/__init__.py
pystocktopus/__main__.py
pystocktopus/config.py
pystocktopus/core.py
pystocktopus/main.py
pystocktopus/news_analysis.py
pystocktopus/pattern_tool.py
pystocktopus/stock_csv.py
pystocktopus/stock_data.csv
pystocktopus/stock_forecasting.py
pystocktopus/Data/Pattern/ascending_triangle.json
pystocktopus-0.1.8.dist-info/METADATA
pystocktopus-0.1.8.dist-info/WHEEL
pystocktopus-0.1.8.dist-info/licenses/LICENSE
pystocktopus-0.1.8.dist-info/RECORD
