Metadata-Version: 2.3
Name: pystocktopus
Version: 0.1.8
Summary: help you maintain your stock dashboard also predict future for a stock based upon past data and also use the news sentiments of stocks volatality
Project-URL: Homepage, https://github.com/Akhil-Sharma30/pystocktopus
Project-URL: Documentation, https://pystocktopus.readthedocs.io/en/latest/
Project-URL: Bug Tracker, https://github.com/Akhil-Sharma30/pystocktopus/issues
Project-URL: Discussions, https://github.com/Akhil-Sharma30/pystocktopus/discussions
Project-URL: Changelog, https://github.com/Akhil-Sharma30/pystocktopus/releases
Author-email: Akhil Sharma <akhilsharma.off@gmail.com>
License-File: LICENSE
Classifier: Development Status :: 1 - Planning
Classifier: Intended Audience :: Developers
Classifier: Intended Audience :: Science/Research
Classifier: License :: OSI Approved :: GNU General Public License v3 or later (GPLv3+)
Classifier: Operating System :: OS Independent
Classifier: Programming Language :: Python
Classifier: Programming Language :: Python :: 3
Classifier: Programming Language :: Python :: 3 :: Only
Classifier: Programming Language :: Python :: 3.8
Classifier: Programming Language :: Python :: 3.9
Classifier: Programming Language :: Python :: 3.10
Classifier: Programming Language :: Python :: 3.11
Classifier: Programming Language :: Python :: 3.12
Classifier: Topic :: Scientific/Engineering
Classifier: Typing :: Typed
Requires-Python: >=3.8
Requires-Dist: matplotlib
Requires-Dist: mplfinance
Requires-Dist: newsapi-python
Requires-Dist: pandas
Requires-Dist: plotly
Requires-Dist: pmdarima
Requires-Dist: polygon-api-client
Requires-Dist: scikit-learn
Requires-Dist: tensorflow
Requires-Dist: transformers
Requires-Dist: typing
Requires-Dist: urllib3
Provides-Extra: dev
Requires-Dist: pytest; extra == 'dev'
Requires-Dist: pytest-cov; extra == 'dev'
Provides-Extra: docs
Requires-Dist: furo; extra == 'docs'
Requires-Dist: mkdocs-material; extra == 'docs'
Requires-Dist: myst-parser; extra == 'docs'
Requires-Dist: sphinx-autodoc-typehints; extra == 'docs'
Requires-Dist: sphinx-copybutton; extra == 'docs'
Provides-Extra: test
Requires-Dist: pytest; extra == 'test'
Requires-Dist: pytest-cov; extra == 'test'
